[{"name":"type","type":"number","conditions":"true"},{"name":"remove","type":"number","conditions":"true"},{"name":"status","type":"number","conditions":"true"},{"name":"unit_id","type":"number","conditions":"true"},{"name":"duration","type":"number","conditions":"true"},{"name":"end_date","type":"datetime","conditions":"true"},{"name":"owner_id","type":"number","conditions":"true"},{"name":"tenant_id","type":"number","conditions":"true"},{"name":"company_id","type":"number","conditions":"true"},{"name":"owner_type","type":"number","conditions":"true"},{"name":"start_date","type":"datetime","conditions":"true"},{"name":"date_create","type":"datetime","conditions":"true"},{"name":"landlord_id","type":"number","conditions":"true"},{"name":"property_id","type":"number","conditions":"true"},{"name":"no_submitted","type":"number","conditions":"true"},{"name":"with_parking","type":"number","conditions":"true"},{"name":"no_of_renewal","type":"number","conditions":"true"},{"name":"license_number","type":"number","conditions":"true"},{"name":"security_deposit","type":"money","conditions":"true"},{"name":"status_signature","type":"number","conditions":"true"},{"name":"applications_fees","type":"money","conditions":"true"},{"name":"total_rent_amount","type":"money","conditions":"true"},{"name":"application_number","type":"number","conditions":"true"},{"name":"no_of_installments","type":"number","conditions":"true"},{"name":"owner_signature_date","type":"datetime","conditions":"true"},{"name":"tenant_signature_date","type":"datetime","conditions":"true"},{"name":"terms_and_conditions_ar","type":"text","conditions":"true"},{"name":"terms_and_conditions_en","type":"text","conditions":"true"}]