{
            "name": "Marketplace",
            "data": [
                {
                "Type": "pages",
                "Name": "AddOffer",
                "Value": "Div(Class: row df f-valign){\r\n\tDiv(Class: col-md-2)\r\n\tDiv(Class: col-md-8){\r\n\t\tForm(){\r\n\t\t\tDiv(Class: panel panel-default){\r\n\t\t\t\tDiv(Class: list-group-item text-center){\r\n\t\t\t\t\tP(Class: h2 text-bold m0, Body: Invitation for Bid)\r\n\t\t\t\t}\r\n\t\t\t\tDiv(Class: list-group-item text-center){\r\n\t\t\t\t\tDiv(Class: row df f-valign){\r\n\t\t\t\t\t\tDiv(Class: col-md-6 mt-sm text-right){\r\n\t\t\t\t\t\t\tP(Class: h5 text-normal m0){\r\n\t\t\t\t\t\t\t\tSpan(Class: h4 text-bold, Body: Type of Note)\r\n\t\t\t\t\t\t\t}\r\n\t\t\t\t\t\t}.Style(padding-top: 5px;)\r\n\t\t\t\t\t\tDiv(Class: col-md-3 mt-sm){\r\n\t\t\t\t\t\t\tInput(TypeNote,Disabled:\"true\",Value: Commercial Paper)\r\n\t\t\t\t\t\t}\r\n\t\t\t\t\t}\r\n\t\t\t\t\tDiv(Class: row df f-valign){\r\n\t\t\t\t\t\tDiv(Class: col-md-6 mt-sm text-right){\r\n\t\t\t\t\t\t\tP(Class: h5 text-normal m0){\r\n\t\t\t\t\t\t\t\tSpan(Class: h4 text-bold, Body: Aggregate Principal Amount)\r\n\t\t\t\t\t\t\t}\r\n\t\t\t\t\t\t}.Style(padding-top: 5px;)\r\n\t\t\t\t\t\tDiv(Class: col-md-3 mt-sm){\r\n\t\t\t\t\t\t\tInput(AgregatPA)\r\n\t\t\t\t\t\t}\r\n\t\t\t\t\t}\r\n\t\t\t\t}\r\n\t\t\t\tDiv(Class: list-group-item text-center){\r\n\t\t\t\t\tDiv(Class: row df f-valign){\r\n\t\t\t\t\t\tDiv(Class: col-md-6 mt-sm text-right){\r\n\t\t\t\t\t\t\tP(Class: h5 text-normal m0){\r\n\t\t\t\t\t\t\t\tSpan(Class: h4 text-bold, Body: Guarantor)\r\n\t\t\t\t\t\t\t}\r\n\t\t\t\t\t\t}.Style(padding-top: 5px;)\r\n\t\t\t\t\t\tDiv(Class: col-md-3 mt-sm){\r\n\t\t\t\t\t\t\tInput(Guarantor)\r\n\t\t\t\t\t\t}\r\n\t\t\t\t\t}\r\n\t\t\t\t\tDiv(Class: row df f-valign){\r\n\t\t\t\t\t\tDiv(Class: col-md-6 mt-sm text-right){\r\n\t\t\t\t\t\t\tP(Class: h5 text-normal m0){\r\n\t\t\t\t\t\t\t\tSpan(Class: h4 text-bold, Body: Issue Date)\r\n\t\t\t\t\t\t\t}\r\n\t\t\t\t\t\t}.Style(padding-top: 5px;)\r\n\t\t\t\t\t\tDiv(Class: col-md-3 mt-sm){\r\n\t\t\t\t\t\t\tInput(IssueDate,Type: \"date\")\r\n\t\t\t\t\t\t}\r\n\t\t\t\t\t}\r\n\t\t\t\t\tDiv(Class: row df f-valign){\r\n\t\t\t\t\t\tDiv(Class: col-md-6 mt-sm text-right){\r\n\t\t\t\t\t\t\tP(Class: h5 text-normal m0){\r\n\t\t\t\t\t\t\t\tSpan(Class: h4 text-bold, Body: Maturity Date)\r\n\t\t\t\t\t\t\t}\r\n\t\t\t\t\t\t}.Style(padding-top: 5px;)\r\n\t\t\t\t\t\tDiv(Class: col-md-3 mt-sm){\r\n\t\t\t\t\t\t\tInput(MaturityDate,Type: \"date\")\r\n\t\t\t\t\t\t}\r\n\t\t\t\t\t}\r\n\t\t\t\t\tDiv(Class: row df f-valign){\r\n\t\t\t\t\t\tDiv(Class: col-md-6 mt-sm text-right){\r\n\t\t\t\t\t\t\tP(Class: h5 text-normal m0){\r\n\t\t\t\t\t\t\t\tSpan(Class: h4 text-bold, Body: Delivery)\r\n\t\t\t\t\t\t\t}\r\n\t\t\t\t\t\t}.Style(padding-top: 5px;)\r\n\t\t\t\t\t\tDiv(Class: col-md-3 mt-sm){\r\n\t\t\t\t\t\t\tInput(Delivery)\r\n\t\t\t\t\t\t}\r\n\t\t\t\t\t}\r\n\t\t\t\t\tDiv(Class: row df f-valign){\r\n\t\t\t\t\t\tDiv(Class: col-md-6 mt-sm text-right){\r\n\t\t\t\t\t\t\tP(Class: h5 text-normal m0){\r\n\t\t\t\t\t\t\t\tSpan(Class: h4 text-bold, Body: Listing and admission to trading)\r\n\t\t\t\t\t\t\t}\r\n\t\t\t\t\t\t}.Style(padding-top: 5px;)\r\n\t\t\t\t\t\tDiv(Class: col-md-3 mt-sm){\r\n\t\t\t\t\t\t\tInput(ListingTrading)\r\n\t\t\t\t\t\t}\r\n\t\t\t\t\t}\r\n\t\t\t\t\tDiv(Class: row df f-valign){\r\n\t\t\t\t\t\tDiv(Class: col-md-6 mt-sm text-right){\r\n\t\t\t\t\t\t\tP(Class: h5 text-normal m0){\r\n\t\t\t\t\t\t\t\tSpan(Class: h4 text-bold, Body: Ratings)\r\n\t\t\t\t\t\t\t}\r\n\t\t\t\t\t\t}.Style(padding-top: 5px;)\r\n\t\t\t\t\t\tDiv(Class: col-md-3 mt-sm){\r\n\t\t\t\t\t\t\tInput(Ratings)\r\n\t\t\t\t\t\t}\r\n\t\t\t\t\t}.Style()\r\n\t\t\t\t}\r\n\t\t\t\tDiv(Class: list-group-item text-center){\r\n\t\t\t\t\tP(Class: h2 text-bold m0, Body: Offer For Bid)\r\n\t\t\t\t}.Style(padding-top: 15px;)\r\n\t\t\t\tDiv(Class: list-group text-center){\r\n\t\t\t\t\tDiv(Class: row df f-valign){\r\n\t\t\t\t\t\tDiv(Class: col-md-6 mt-sm text-right){\r\n\t\t\t\t\t\t\tP(Class: h5 text-normal m0){\r\n\t\t\t\t\t\t\t\tSpan(Class: h4 text-bold, Body: Start Date)\r\n\t\t\t\t\t\t\t}.Style(padding-top: 5px;)\r\n\t\t\t\t\t\t}.Style(padding-top: 5px;)\r\n\t\t\t\t\t\tDiv(Class: col-md-3 mt-sm text-left){\r\n\t\t\t\t\t\t\tInput(StartInvaite,Type: \"date\")\r\n\t\t\t\t\t\t}\r\n\t\t\t\t\t}\r\n\t\t\t\t\tDiv(Class: row df f-valign){\r\n\t\t\t\t\t\tDiv(Class: col-md-6 mt-sm text-right){\r\n\t\t\t\t\t\t\tP(Class: h5 text-normal m0){\r\n\t\t\t\t\t\t\t\tSpan(Class: h4 text-bold, Body: End Date)\r\n\t\t\t\t\t\t\t}.Style(padding-top: 5px;)\r\n\t\t\t\t\t\t}.Style(padding-top: 5px;)\r\n\t\t\t\t\t\tDiv(Class: col-md-3 mt-sm){\r\n\t\t\t\t\t\t\tInput(EndInvaite,Type: \"date\")\r\n\t\t\t\t\t\t}\r\n\t\t\t\t\t}.Style(padding-bottom: 20px;)\r\n\t\t\t\t}.Style(padding-top: 10px;)\r\n\t\t\t\tDiv(Class: panel-footer text-right){\r\n\t\t\t\t\tButton(Save,Class: btn btn-primary pull-right,Contract: addOffer,Page:ListingOffer)\r\n\t\t\t\t}.Style(height: 55px;)\r\n\t\t\t}\r\n\t\t}\r\n\t}\r\n}",
                "Conditions": "true",
                "Menu": "default_menu",
                "Title": "",
                "Trans": "",
                "Columns": "",
                "Permissions": ""
            },
{
                "Type": "pages",
                "Name": "ListingOffer",
                "Value": "SetTitle(List of Invitations for Bid)\r\nAddToolButton(Title: Add, Page: AddOffer, Icon: icon-plus)\r\nDiv(Class: content-wrapper){\r\n    DBFind(\"form_of_listing\",Source: src_form).Custom(src_gobutton){\r\n        Div(pull-right){\r\n            Button(View,Class: btn btn-primary,Page: ViewOffer ,PageParams:\"offer_id=#id#\")\r\n        }\r\n    }.Custom(_id){\r\n        Span(Class:h4, Body:#id#)\r\n    }.Custom(_ratings){\r\n        Span(Class:h4, Body:#ratings#)\r\n    }.Custom(_agregat_p_a){\r\n        Span(Class:h4, Body:#agregat_p_a# EUR)\r\n    }.Custom(_type_of_note){\r\n        Span(Class:h4, Body:#type_of_note#)\r\n    }.Custom(_type_of_note){\r\n        Span(Class:h4, Body:#type_of_note#)\r\n    }.Custom(is_date){\r\n        Span(DateTime(DateTime: #issue_date#, Format: \"DD.MM.YYYY\"))\r\n    }.Custom(matur_date){\r\n        Span(DateTime(DateTime: #maturity_date#, Format: \"DD.MM.YYYY\"))\r\n    }.Custom(start_date){\r\n        Span(DateTime(DateTime: #date_start_invaite_sell#, Format: \"DD.MM.YYYY\"))\r\n    }.Custom(end_date){\r\n        Span(DateTime(DateTime: #date_end_invaite_sell#, Format: \"DD.MM.YYYY\"))\r\n    }.Custom(user_image){\r\n        If(#issuer# != 0){\r\n            DBFind(\"members\").WhereId(#issuer#).Vars(img)\r\n            Image(Src: Binary().ById(#img_image_id#)).Style(width: 50px; height 50px;)\r\n            Span(#img_member_name#)\r\n        }\r\n    }.Where(\"deleted=0\")\r\n    Table(Source: src_form, Columns: \"ID=_id,Type=_type_of_note,Issuer=user_image,Guarantor=guarantor,Amount=src_amount,Delivery=delivery,Issue Date=is_date,Maturity Date=matur_date,Start Date=start_date,End Date=end_date,Ratings=_ratings,Aggregate Principal Amount=_agregat_p_a,=src_gobutton\").Style(\r\n        th{\r\n            color:#000!important;\r\n            font-weight:bold!important;\r\n        }\r\n        tbody tr:nth-child(odd){\r\n            background: #f8f8f8;\r\n        }\r\n        thead{\r\n            background: #586180;\r\n        \tcolor: white;\r\n        }\r\n        th{\r\n            color: #FFFFFF!important;\r\n        }\r\n    )\r\n}",
                "Conditions": "true",
                "Menu": "default_menu",
                "Title": "",
                "Trans": "",
                "Columns": "",
                "Permissions": ""
            },
{
                "Type": "pages",
                "Name": "ViewOffer",
                "Value": "DBFind(\"form_of_listing\").WhereId(#offer_id#).Custom(issue_dates){\r\n\tDateTime(#issue_date#, \"DD-MM-YYYY\")\r\n}.Vars(pre)\r\n\r\nDiv(Class: row df f-valign){\r\n\tDiv(Class: col-md-2)\r\n\tDiv(Class: col-md-8){\r\n\t\tDiv(Class: panel panel-default){\r\n\t\t\tForm(){\r\n\t\t\t\tDiv(Class: list-group-item text-center){\r\n\t\t\t\t\tDiv(Class: row df f-valign){\r\n\t\t\t\t\t\tDiv(Class: col-md-12 mt-sm text-center){\r\n\t\t\t\t\t\t\tP(Class: h5 text-normal m0){\r\n\t\t\t\t\t\t\t\tSpan(Class: h2 text-bold, Body: #pre_type_of_note#)\r\n\t\t\t\t\t\t\t}.Style(padding-bottom: 13px;)\r\n\t\t\t\t\t\t}\r\n\t\t\t\t\t}\r\n \t\t\t\t\tDiv(Class: row df f-valign){\r\n\t\t\t\t\t\tDiv(Class: col-md-6 mc-sm text-right){\r\n\t\t\t\t\t\t\tP(Class: h3 text-normal m0){\r\n\t\t\t\t\t\t\t\tSpan(Class: text-bold, Body: Ratings)\r\n\t\t\t\t\t\t\t}.Style(padding-bottom: 8px;)\r\n\t\t\t\t\t\t}\r\n\t\t\t\t\t\tDiv(Class: col-md-6 mc-sm text-left){\r\n\t\t\t\t\t\t\tP(Class: h3 text-normal m0){\r\n\t\t\t\t\t\t\t\tSpan(Class: text-normal, Body: #pre_ratings#)\r\n\t\t\t\t\t\t\t}.Style(padding-bottom: 8px;)\r\n\t\t\t\t\t\t}\r\n\t\t\t\t\t}\r\n\t\t\t\t\tDiv(Class: row df f-valign){\r\n\t\t\t\t\t\tDiv(Class: col-md-6 mc-sm text-right){\r\n\t\t\t\t\t\t\tP(Class: h3 text-normal m0){\r\n\t\t\t\t\t\t\t\tSpan(Class: text-bold, Body: Aggregate Principal Amount)\r\n\t\t\t\t\t\t\t}.Style(padding-bottom: 8px;)\r\n\t\t\t\t\t\t}\r\n\t\t\t\t\t\tDiv(Class: col-md-6 mc-sm text-left){\r\n\t\t\t\t\t\t\tP(Class: h3 text-normal m0){\r\n\t\t\t\t\t\t\t\tSpan(Class: text-normal, Body: #pre_agregat_p_a# EUR)\r\n\t\t\t\t\t\t\t}.Style(padding-bottom: 8px;)\r\n\t\t\t\t\t\t}\r\n\t\t\t\t\t}\r\n\t\t\t\t}\r\n\t\t\t\tDiv(Class: list-group-item text-center){\r\n\t\t\t\t\tDiv(Class: row df f-valign){\r\n\t\t\t\t\t\tDiv(Class: col-md-6 mt-sm text-right){\r\n\t\t\t\t\t\t\tP(Class: h4 text-normal m0){\r\n\t\t\t\t\t\t\t\tSpan(Class: text-bold, Body: Issuer)\r\n\t\t\t\t\t\t\t}.Style(padding-top: 15px;)\r\n\t\t\t\t\t\t}\r\n\t\t\t\t\t\tDBFind(\"members\").WhereId(#pre_issuer#).Vars(img)\r\n\t\t\t\t\t\tDiv(Class: col-md-6 mt-sm text-left){\r\n\t\t\t\t\t\t\tP(Class: h4 text-normal m0){\r\n\t\t\t\t\t\t\t\tSpan(Class: text-normal, Body: Image(Src: Binary().ById(#img_image_id#)))\r\n\t\t\t\t\t\t\t\tSpan(Class: h4 text-normal, Body: #img_member_name#)\r\n\t\t\t\t\t\t\t}.Style(padding-bottom: 8px; img {width: 50px; height: 50px;})\r\n\t\t\t\t\t\t}\r\n\t\t\t\t\t}\r\n\t\t\t\t\tDiv(Class: row df f-valign){\r\n\t\t\t\t\t\tDiv(Class: col-md-6 mc-sm text-right){\r\n\t\t\t\t\t\t\tP(Class: h4 text-normal m0){\r\n\t\t\t\t\t\t\t\tSpan(Class: text-bold, Body: Guarantor)\r\n\t\t\t\t\t\t\t}.Style(padding-bottom: 8px;)\r\n\t\t\t\t\t\t}\r\n\t\t\t\t\t\tDiv(Class: col-md-6 mc-sm text-left){\r\n\t\t\t\t\t\t\tP(Class: h4 text-normal m0){\r\n\t\t\t\t\t\t\t\tSpan(Class: text-normal, Body: #pre_guarantor#)\r\n\t\t\t\t\t\t\t}.Style(padding-bottom: 8px;)\r\n\t\t\t\t\t\t}\r\n\t\t\t\t\t}\r\n\t\t\t\t\tDiv(Class: row df f-valign){\r\n\t\t\t\t\t\tDiv(Class: col-md-6 mc-sm text-right){\r\n\t\t\t\t\t\t\tP(Class: h4 text-normal m0){\r\n\t\t\t\t\t\t\t\tSpan(Class: text-bold, Body: Delivery)\r\n\t\t\t\t\t\t\t}.Style(padding-bottom: 8px;)\r\n\t\t\t\t\t\t}\r\n\t\t\t\t\t\tDiv(Class: col-md-6 mc-sm text-left){\r\n\t\t\t\t\t\t\tP(Class: h4 text-normal m0){\r\n\t\t\t\t\t\t\t\tSpan(Class: text-normal, Body: #pre_delivery#)\r\n\t\t\t\t\t\t\t}.Style(padding-bottom: 8px;)\r\n\t\t\t\t\t\t}\r\n\t\t\t\t\t}\r\n\t\t\t\t\tDiv(Class: row df f-valign){\r\n\t\t\t\t\t\tDiv(Class: col-md-6 mc-sm text-right){\r\n\t\t\t\t\t\t\tP(Class: h4 text-normal m0){\r\n\t\t\t\t\t\t\t\tSpan(Class: text-bold, Body: Listing and admission to trading)\r\n\t\t\t\t\t\t\t}.Style(padding-bottom: 8px;)\r\n\t\t\t\t\t\t}\r\n\t\t\t\t\t\tDiv(Class: col-md-6 mc-sm text-left){\r\n\t\t\t\t\t\t\tP(Class: h4 text-normal m0){\r\n\t\t\t\t\t\t\t\tSpan(Class: text-normal, Body: #pre_listing_and_admission_to_tr#)\r\n\t\t\t\t\t\t\t}.Style(padding-bottom: 8px;)\r\n\t\t\t\t\t\t}\r\n\t\t\t\t\t}\r\n\t\t\t\t\tDiv(Class: row df f-valign){\r\n\t\t\t\t\t\tDiv(Class: col-md-6 mt-sm text-right){\r\n\t\t\t\t\t\t\tP(Class: h4 text-normal m0){\r\n\t\t\t\t\t\t\t\tSpan(Class: text-bold, Body: Issue Date)\r\n\t\t\t\t\t\t\t}.Style(padding-bottom: 8px;)\r\n\t\t\t\t\t\t}\r\n\t\t\t\t\t\tDiv(Class: col-md-6 mt-sm text-left){\r\n\t\t\t\t\t\t\tP(Class: h4 text-normal m0){\r\n\t\t\t\t\t\t\t\tSpan(Class: text-normal, Body: DateTime(#pre_issue_date#, \"DD-MM-YYYY\"))\r\n\t\t\t\t\t\t\t}.Style(padding-bottom: 8px;)\r\n\t\t\t\t\t\t}\r\n\t\t\t\t\t}\r\n\t\t\t\t\tDiv(Class: row df f-valign){\r\n\t\t\t\t\t\tDiv(Class: col-md-6 mc-sm text-right){\r\n\t\t\t\t\t\t\tP(Class: h4 text-normal m0){\r\n\t\t\t\t\t\t\t\tSpan(Class: text-bold, Body: Maturity Date)\r\n\t\t\t\t\t\t\t}.Style(padding-bottom: 8px;)\r\n\t\t\t\t\t\t}\r\n\t\t\t\t\t\tDiv(Class: col-md-6 mc-sm text-left){\r\n\t\t\t\t\t\t\tP(Class: h4 text-normal m0){\r\n\t\t\t\t\t\t\t\tSpan(Class: text-normal, Body: DateTime(#pre_maturity_date#, \"DD-MM-YYYY\"))\r\n\t\t\t\t\t\t\t}.Style(padding-bottom: 8px;)\r\n\t\t\t\t\t\t}\r\n\t\t\t\t\t}\r\n\t\t\t\t}\r\n\t\t\t}\r\n\r\n\t\t\r\n\t\t}\r\n\t\tDBFind(\"bidders_invaite\",Source:src_kek).Where(\"offer_invaite_id = #offer_id# and status = 1\").Custom(src_request){\r\n            Div(pull-right){\r\n                    Span(Em(Class: icon-check fa-2x)).Style(color: #586180; padding-right:30px;)      \r\n                }\r\n        }.Custom(user_image){\r\n            DBFind(\"members\").WhereId(#member_id#).Vars(img)\r\n            Image(Src: Binary().ById(#img_image_id#)).Style(height: 50px;width: 50px;)\r\n            Span(#img_member_name#)\r\n        }.Custom(_member_id){\r\n            Span(Class:text-muted, Body:#member_id#)\r\n        }\r\n\r\n\r\n\t\tDiv(Class: panel panel-default){\r\n\t\t\tForm(){\r\n\t            Table(Source: src_kek,Columns:\"=user_image,=_member_id,=src_request\")\r\n            }\r\n\t\t\tDiv(Class: panel-footer text-right){\r\n\t\t\t\tButton(Back,Class: btn btn-default pull-left,Page:ListingOffer)\r\n\t\t\t\tButton(Add Bidders,Class: btn btn-primary pull-right,Page:AddBidders,PageParams:\"offer_id=#offer_id#\")\r\n\t\t\t}.Style(height: 55px;)\r\n        }\r\n\t}\r\n\tDiv(Class: col-md-2)\r\n}",
                "Conditions": "true",
                "Menu": "default_menu",
                "Title": "",
                "Trans": "",
                "Columns": "",
                "Permissions": ""
            },
{
                "Type": "pages",
                "Name": "AddBidders",
                "Value": "Div(Class: content-wrapper){\r\n    DBFind(\"roles_participants\",Source:src_mem).Columns(\"id,member,deleted,role->name,member->member_name,member->member_id\").Where(\"deleted = 0 and role->name='Buyers'\").Custom(src_request){\r\n        SetVar(pre_id,0)\r\n        DBFind(\"bidders_invaite\",Source:src_kek).Where(\"member_id = #member.member_id# and offer_invaite_id = #offer_id#\").Vars(pre)\r\n        Div(pull-right){\r\n                If(#pre_id# == 0){\r\n                    Button(Add,Class: btn btn-primary,Contract:addBidders,Page:AddBidders,Params:\"IdOffer=#offer_id#,IdBuyes=#member.member_id#\",PageParams:\"offer_id=#offer_id#\")\r\n                }.Else{\r\n                    Span(Em(Class: icon-check fa-2x)).Style(color: #586180; padding-right:18px;)   \r\n                }\r\n            }\r\n        }.Custom(user_image){\r\n            DBFind(\"members\").WhereId(#member.member_id#).Vars(img)\r\n            Image(Src: Binary().ById(#img_image_id#)).Style(height: 50px;width: 50px;)\r\n            Span(#img_member_name#)\r\n        }.Custom(_member_id){\r\n            Span(Class:text-muted, Body:#member.member_id#)\r\n        }\r\n    Table(Source: src_mem,Columns:\"Member Name=user_image,Member ID=_member_id,Role=role.name,=src_request\").Style(\r\n        th{\r\n            color:#000!important;\r\n            font-weight:bold!important;\r\n        }\r\n        tbody tr:nth-child(odd){\r\n            background: #f8f8f8;\r\n        }\r\n        thead{\r\n            background: #586180;\r\n            color: white;\r\n        }\r\n        th{\r\n            color: #FFFFFF!important;\r\n        }\r\n    )\r\n}",
                "Conditions": "true",
                "Menu": "default_menu",
                "Title": "",
                "Trans": "",
                "Columns": "",
                "Permissions": ""
            },
{
                "Type": "pages",
                "Name": "ListingOffer2",
                "Value": "SetTitle(List of Invitations for Bid)\r\nDiv(Class: content-wrapper){\r\n    DBFind(\"form_of_listing\",Source: src_form).Custom(src_gobutton){\r\n        Div(pull-right){\r\n            Button(StartSelling,Class: btn btn-primary,Contract:StartSelling,Params:\"OfferId=#id#\", Page:ListingOffer)\r\n            Button(EndSelling,Class: btn btn-danger,Contract:EndSelling,Params:\"OfferId=#id#\", Page:ListingOffer)\r\n        }\r\n    }.Custom(src_gobutton2){\r\n        Div(pull-right){\r\n            Button(Del,Class: btn btn-danger,Contract:delOffer,Params:\"offer_id=#id#\", Page:ListingOffer)\r\n        }\r\n    }.Custom(is_date){\r\n        Span(DateTime(DateTime: #issue_date#, Format: \"DD.MM.YYYY\"))\r\n    }.Custom(matur_date){\r\n        Span(DateTime(DateTime: #maturity_date#, Format: \"DD.MM.YYYY\"))\r\n    }.Custom(start_date){\r\n        Span(DateTime(DateTime: #date_start_invaite_sell#, Format: \"DD.MM.YYYY\"))\r\n    }.Custom(end_date){\r\n        Span(DateTime(DateTime: #date_end_invaite_sell#, Format: \"DD.MM.YYYY\"))\r\n    }.Where(\"deleted=0\")\r\n    Table(Source: src_form,Columns: \"ID=id,Type=type_of_note,Aggregate Principal Amount=agregat_p_a,Start Date=start_date,End Date=end_date,=src_gobutton,=src_gobutton2\").Style(\r\n        th{\r\n            color:#000!important;\r\n            font-weight:bold!important;\r\n        }\r\n        td{\r\n        }\r\n        tbody tr:nth-child(odd){\r\n            background: #f8f8f8;\r\n        }\r\n        thead{\r\n            background: #586180;\r\n        \tcolor: white;\r\n        }\r\n        th{\r\n            color: #FFFFFF!important;\r\n        }\r\n    )\r\n}",
                "Conditions": "true",
                "Menu": "admin_menu",
                "Title": "",
                "Trans": "",
                "Columns": "",
                "Permissions": ""
            },
{
                "Type": "pages",
                "Name": "PageSellingOffer",
                "Value": "If(#notific_id# > 0){\r\n    DBFind(\"notifications\",Source:src_mem).Columns(\"id,page_params->offer_id,page_params->invaite_id,recipient->member_id\").WhereId(#notific_id#).Vars(mem)\r\n    DBFind(\"form_of_listing\").WhereId(#mem_page_params_offer_id#).Custom(issue_dates){\r\n        DateTime(#issue_date#, \"DD-MM-YYYY\")\r\n    }.Vars(pre)\r\n        Div(Class: row df f-valign){\r\n            Div(Class: col-md-2)\r\n            Div(Class: col-md-8){\r\n                Div(Class: panel panel-default){\r\n                    Form(){\r\n                        Div(Class: list-group-item){\r\n                            Div(Class: row df f-valign){\r\n                                Div(Class: col-md-12 mc-sm text-center){\r\n                                    P(Class: h5 text-normal m0){\r\n                                        Span(Class: h2 text-bold, Body: #pre_type_of_note#)\r\n                                    }.Style(padding-bottom: 8px;)\r\n                                }\r\n                            }\r\n                            Div(Class: row df f-valign){\r\n                                 Div(Class: col-md-6 mc-sm text-right){\r\n                                    P(Class: h3 text-normal m0){\r\n                                        Span(Class: text-bold, Body: Ratings)\r\n                                    }.Style(padding-bottom: 8px;)\r\n                                }\r\n                                Div(Class: col-md-6 mc-sm text-left){\r\n                                    P(Class: h3 text-normal m0){\r\n                                        Span(Class: text-normal, Body: #pre_ratings#)\r\n                                    }.Style(padding-bottom: 8px;)\r\n                                }\r\n\r\n\r\n                            }\r\n                            Div(Class: row df f-valign){\r\n                                Div(Class: col-md-6 mc-sm text-right){\r\n                                    P(Class: h3 text-normal m0){\r\n                                        Span(Class: text-bold, Body: Aggregate Principal Amount)\r\n                                    }.Style(padding-bottom: 8px;)\r\n                                }\r\n                                Div(Class: col-md-6 mc-sm text-left){\r\n                                    P(Class: h3 text-normal m0){\r\n                                        Span(Class: text-normal, Body: #pre_agregat_p_a# EUR)\r\n                                    }.Style(padding-bottom: 8px;)\r\n                                }\r\n                            }\r\n                        }\r\n                        Div(Class: list-group-item text-center){\r\n                            Div(Class: row df f-valign){\r\n                                Div(Class: col-md-6 mt-sm text-right){\r\n                                    P(Class: h4 text-normal m0){\r\n                                        Span(Class: text-bold, Body: Issuer)\r\n                                    }.Style(padding-top: 15px;)\r\n                                }\r\n                                DBFind(\"members\").WhereId(#pre_issuer#).Vars(img)\r\n                                Div(Class: col-md-6 mt-sm text-left){\r\n                                    P(Class: h4 text-normal m0){\r\n                                        Span(Class: text-normal, Body: Image(Src: Binary().ById(#img_image_id#)))\r\n                                        Span(Class: h4 text-normal, Body: #img_member_name#)\r\n                                    }.Style(padding-bottom: 8px; img {width: 50px; height: 50px;})\r\n                                }\r\n                            }\r\n                            Div(Class: row df f-valign){\r\n                                Div(Class: col-md-6 mc-sm text-right){\r\n                                    P(Class: h4 text-normal m0){\r\n                                        Span(Class: text-bold, Body: Guarantor)\r\n                                    }.Style(padding-bottom: 8px;)\r\n                                }\r\n                                Div(Class: col-md-6 mc-sm text-left){\r\n                                    P(Class: h4 text-normal m0){\r\n                                        Span(Class: text-normal, Body: #pre_guarantor#)\r\n                                    }.Style(padding-bottom: 8px;)\r\n                                }\r\n                            }\r\n                            Div(Class: row df f-valign){\r\n                                Div(Class: col-md-6 mc-sm text-right){\r\n                                    P(Class: h4 text-normal m0){\r\n                                        Span(Class: text-bold, Body: Delivery)\r\n                                    }.Style(padding-bottom: 8px;)\r\n                                }\r\n                                Div(Class: col-md-6 mc-sm text-left){\r\n                                    P(Class: h4 text-normal m0){\r\n                                        Span(Class: text-normal, Body: #pre_delivery#)\r\n                                    }.Style(padding-bottom: 8px;)\r\n                                }\r\n                            }\r\n                            Div(Class: row df f-valign){\r\n                                Div(Class: col-md-6 mc-sm text-right){\r\n                                    P(Class: h4 text-normal m0){\r\n                                        Span(Class: text-bold, Body: Listing and admission to trading)\r\n                                    }.Style(padding-bottom: 8px;)\r\n                                }\r\n                                Div(Class: col-md-6 mc-sm text-left){\r\n                                    P(Class: h4 text-normal m0){\r\n                                        Span(Class: text-normal, Body: #pre_listing_and_admission_to_tr#)\r\n                                    }.Style(padding-bottom: 8px;)\r\n                                }\r\n                            } \r\n                            Div(Class: row df f-valign){\r\n                                Div(Class: col-md-6 mt-sm text-right){\r\n                                    P(Class: h4 text-normal m0){\r\n                                        Span(Class: text-bold, Body: Issue Date)\r\n                                    }.Style(padding-bottom: 8px;)\r\n                                }\r\n                                Div(Class: col-md-6 mt-sm text-left){\r\n                                    P(Class: h4 text-normal m0){\r\n                                      Span(Class: text-normal, Body: DateTime(#pre_issue_date#, \"DD-MM-YYYY\"))\r\n                                    }.Style(padding-bottom: 8px;)\r\n                                }\r\n                            }\r\n                            Div(Class: row df f-valign){\r\n                                Div(Class: col-md-6 mc-sm text-right){\r\n                                    P(Class: h4 text-normal m0){\r\n                                        Span(Class: text-bold, Body: Maturity Date)\r\n                                    }.Style(padding-bottom: 8px;)\r\n                                }\r\n                                Div(Class: col-md-6 mc-sm text-left){\r\n                                    P(Class: h4 text-normal m0){\r\n                                        Span(Class: text-normal, Body: DateTime(#pre_maturity_date#, \"DD-MM-YYYY\"))\r\n                                    }.Style(padding-bottom: 8px;)\r\n                                }\r\n                            }\r\n                            Div(Class: list-group-item row df f-valign){\r\n                                Div(Class: col-md-6 mc-sm text-right){\r\n                                    P(Class: h4 text-normal m0){\r\n                                        Span(Class: text-bold, Body: Please indicate your offer to pay in APL tokens)\r\n                                    }.Style(padding-top: 4px;)\r\n                                }\r\n                                Div(Class: col-md-6 mc-sm text-left){\r\n                                    P(Class: h4 text-normal m0){\r\n                                        Input(AmountOffer)\r\n                                    }.Style(padding-bottom: 8px;)\r\n                                }\r\n                            }.Style(padding-top: 18px;)\r\n                        }.Style(padding-bottom: 0px;)\r\n                        Div(Class: panel-footer text-right){\r\n                            Button(Reject,Class: btn btn-danger pull-left,Page:ListingOffer,Contract:notifications_Close,Params:\"notific_id=#notific_id#\")\r\n                            Button(Send,Class: btn btn-primary pull-right,Page:ListingOffer,Contract: SendAmountOffer,Params:\"AmountOffer=Val(AmountOffer),OfferId=#mem_page_params_offer_id#,InvaiteId=#mem_page_params_invaite_id#,Notific_id=#notific_id#\")\r\n                        }.Style(height: 55px;)\r\n                    }\r\n                }\r\n            }\r\n        }\r\n        Div(Class: col-md-2)\r\n    }",
                "Conditions": "true",
                "Menu": "default_menu",
                "Title": "",
                "Trans": "",
                "Columns": "",
                "Permissions": ""
            },
{
                "Type": "pages",
                "Name": "IFBResults",
                "Value": "If(#notific_id# > 0){\r\nDiv(Class: contant-wrapper){\r\n        DBFind(\"notifications\").Columns(\"id,page_params->win_id,page_params->offer_id\").WhereId(#notific_id#).Vars(pre)\r\n        \r\n        DBFind(\"bidders_invaite\",Source: src_mem).Where(\"offer_invaite_id = #pre_page_params_offer_id#\").Custom(user_image){\r\n            DBFind(\"members\").WhereId(#member_id#).Vars(img)\r\n            Image(Src: Binary().ById(#img_image_id#)).Style(width: 50px; height 50px;)\r\n            Span(#img_member_name#)\r\n        }.Custom(_member_id){\r\n            Span(Class:text-muted, Body:#member_id#)\r\n        }.Custom(_amount){\r\n            Div(pull-right){\r\n                Span(Class:text-bold h4, Body:#amount# APL)\r\n            }\r\n        }\r\n\r\n            Div(Class: col-md-2)\r\n            Div(Class: col-md-8){\r\n            Div(Class: panel panel-default){\r\n            Div(Class: list-group-item text-center){\r\n                P(Class: h2 text-bold m0, Body: IFB Results)\r\n            }\r\n            Div(Class: list-group-item){\r\n                Div(Class: row df f-valign){\r\n                    Div(Class: col-md-12 mt-sm){\r\n                        DBFind(\"bidders_invaite\").Where(\"id = #pre_page_params_win_id#\").Vars(memb)\r\n                        DBFind(\"members\").WhereId(#memb_member_id#).Vars(win)\r\n                        Table(Source: src_mem,Columns:\"=user_image,=_member_id,=_amount\")\r\n\t\t\t\t\t}\r\n                }\r\n            }\r\n            Div(Class: list-group-item){\r\n                Div(text-center){\r\n                    Span(Class: h4 text-bold, Body: The best offer has been submitted by the Span(Class: h3 text-warning, Body: #win_member_name#) with the price offer of Span(Class: h3 text-warning, Body: #memb_amount# APL)).Style(padding-top: 10px)\r\n                }\r\n            }\r\n            Div(panel-footer){\r\n                Button(Accept,Class: btn btn-primary pull-right,Contract:SendCustodian,Params:\"WinMemberId = #memb_member_id#,Notific_id=#notific_id#,OfferId=#pre_page_params_offer_id#,WinAmount=#memb_amount#\",Page:ListingOffer)\r\n                Button(Reject,Class: btn btn-danger pull-left,Contract:notifications_Close,Params:\"notific_id=#notific_id#\")\r\n            }.Style(height: 55px;)\r\n        }\r\n    }\r\n}",
                "Conditions": "true",
                "Menu": "default_menu",
                "Title": "",
                "Trans": "",
                "Columns": "",
                "Permissions": ""
            },
{
                "Type": "contracts",
                "Name": "addOffer",
                "Value": "contract addOffer{\r\n    data {\r\n        TypeNote string\r\n\t\tAgregatPA int\r\n\t\tGuarantor string\r\n\t\tIssueDate string \"date\"\r\n\t\tMaturityDate string \"date\"\r\n\t\tDelivery string\r\n\t\tListingTrading string\r\n\t\tRatings string\r\n\t\tStartInvaite string \"date\"\r\n\t\tEndInvaite string \"date\"\r\n    }\r\n    conditions {\r\n\r\n    }\r\n    action {\r\n        DBInsert(\"form_of_listing\",\"type_of_note,agregat_p_a,issuer,guarantor,issue_date,maturity_date,delivery,listing_and_admission_to_tr,ratings,date_start_invaite_sell,date_end_invaite_sell\",\r\n\t\t   $TypeNote,$AgregatPA,$key_id,$Guarantor,$IssueDate,$MaturityDate,$Delivery,$ListingTrading,$Ratings,$StartInvaite,$EndInvaite)\r\n    }\r\n}",
                "Conditions": "true",
                "Menu": "",
                "Title": "",
                "Trans": "",
                "Columns": "",
                "Permissions": ""
            },
{
                "Type": "contracts",
                "Name": "addBidders",
                "Value": "contract addBidders {\r\n    data {\r\n        IdOffer int\r\n        IdBuyes int\r\n    }\r\n    conditions {\r\n\r\n    }\r\n    action {\r\n        DBInsert(\"bidders_invaite\",\"member_id,offer_invaite_id,status\",$IdBuyes,$IdOffer,1)\r\n    }\r\n}",
                "Conditions": "true",
                "Menu": "",
                "Title": "",
                "Trans": "",
                "Columns": "",
                "Permissions": ""
            },
{
                "Type": "contracts",
                "Name": "StartSelling",
                "Value": "contract StartSelling {\r\n    data {\r\n        OfferId int\r\n    }\r\n    conditions {\r\n\r\n    }\r\n    action {\r\n        var ret map\r\n        var i int\r\n        ret = DBFind(\"bidders_invaite\").Where(\"offer_invaite_id = ? and status = ?\",$OfferId,1)\r\n        while i < Len(ret) {\r\n            var vals map\r\n            vals = ret[i]\r\n\r\n            var mydata map\r\n            mydata[\"invaite_id\"] = vals[\"id\"]\r\n            mydata[\"offer_id\"] = $OfferId\r\n            var params_map string\r\n            params_map = JSONEncode(mydata)\r\n\r\n            notifications_Send(\"member_id,sender,icon_name,text_header,text_body,page_name,params_map\",vals[\"member_id\"],1,\"fa-bell\",\"You are invited for bid\",\"Need your confirmation\",\"PageSellingOffer\",params_map)\r\n            i = i + 1\r\n        }\r\n    }\r\n}",
                "Conditions": "true",
                "Menu": "",
                "Title": "",
                "Trans": "",
                "Columns": "",
                "Permissions": ""
            },
{
                "Type": "contracts",
                "Name": "SendAmountOffer",
                "Value": "contract SendAmountOffer {\r\n    data {\r\n        AmountOffer int\r\n        OfferId int\r\n        InvaiteId int\r\n        Notific_id int\r\n    }\r\n    conditions {\r\n        \r\n    }\r\n    action {\r\n        DBUpdate(\"bidders_invaite\",$InvaiteId,\"amount\",$AmountOffer)\r\n        notifications_Close(\"notific_id\",$Notific_id)\r\n    }\r\n}",
                "Conditions": "true",
                "Menu": "",
                "Title": "",
                "Trans": "",
                "Columns": "",
                "Permissions": ""
            },
{
                "Type": "contracts",
                "Name": "EndSelling",
                "Value": "contract EndSelling {\r\n    data {\r\n        OfferId int\r\n    }\r\n    conditions {\r\n\r\n    }\r\n    action {\r\n        var let map\r\n        let = DBFind(\"bidders_invaite\").Where(\"offer_invaite_id = ?\", $OfferId).Order(\"amount desc\").Row()\r\n\r\n        var params_map map\r\n        params_map[\"win_id\"]=let[\"id\"]\r\n        params_map[\"offer_id\"]=$OfferId\r\n        notifications_Send(\"member_id,sender,icon_name,text_header,text_body,page_name,params_map\",\"-7788010469715397685\",1,\"fa-bell\",\"Trades are over\",\"Need your confirmation\",\"IFBResults\",params_map)\r\n    }\r\n}",
                "Conditions": "true",
                "Menu": "",
                "Title": "",
                "Trans": "",
                "Columns": "",
                "Permissions": ""
            },
{
                "Type": "contracts",
                "Name": "SendCustodian",
                "Value": "contract SendCustodian {\r\n    data {\r\n        WinMemberId int\r\n        Notific_id int\r\n        OfferId int\r\n        WinAmount int\r\n    }\r\n    conditions {\r\n\r\n    }\r\n    action {\r\n        var issue int\r\n        issue = Random(100000,999999)\r\n\r\n        var let map\r\n        let = DBFind(\"form_of_listing\").Where(\"id = ?\",$OfferId).Row()\r\n        var new_id int\r\n        let[\"delivery\"]\r\n        new_id = DBInsert(\"@3_form_of_listing2\",\"agregat_p_a,clearing_system,dealer,delivery,payment,guarantor,isin,issue_date,issuer,listing_agent,listing_and_admission_to_tr,maturity_date,ratings,type_of_note\",\r\n        let[\"agregat_p_a\"],let[\"clearing_system\"],$WinMemberId,let[\"delivery\"],$WinAmount,let[\"guarantor\"],issue,let[\"issue_date\"],let[\"issuer\"],let[\"listing_agent\"],let[\"listing_and_admission_to_tr\"],let[\"maturity_date\"],let[\"ratings\"],let[\"type_of_note\"])\r\n        \r\n        var eco string\r\n        eco = \"3\"\r\n\r\n        var params_map map\r\n        params_map[\"offer_id\"] = new_id\r\n\r\n        notifications_Send(\"member_id,sender,text_header,text_body,page_name,params_map,eco\", $WinMemberId,1,\"Commercial Paper\",\"Commercial Paper has been registered\",\"notifications_default\",params_map,eco)\r\n        notifications_Send(\"member_id,sender,text_header,text_body,page_name,params_map,eco\", -7788010469715397685,1,\"Commercial Paper\",\"Commercial Paper has been registered\",\"notifications_default\",params_map,eco)\r\n\r\n        notifications_Close(\"notific_id\",$Notific_id)\r\n    }\r\n}",
                "Conditions": "true",
                "Menu": "",
                "Title": "",
                "Trans": "",
                "Columns": "",
                "Permissions": ""
            },
{
                "Type": "contracts",
                "Name": "delOffer",
                "Value": "contract delOffer{\r\n    data {\r\n        offer_id int\r\n    }\r\n    conditions {\r\n\r\n    }\r\n    action {\r\n        DBUpdate(\"form_of_listing\", $offer_id, \"deleted\", 1)\r\n    }\r\n}",
                "Conditions": "true",
                "Menu": "",
                "Title": "",
                "Trans": "",
                "Columns": "",
                "Permissions": ""
            },
{
                "Type": "tables",
                "Name": "form_of_listing",
                "Value": "",
                "Conditions": "ContractAccess(\"@1EditTable\")",
                "Menu": "",
                "Title": "",
                "Trans": "",
                "Columns": "[{\"conditions\":\"true\",\"name\":\"status\",\"type\":\"text\"},{\"conditions\":\"true\",\"name\":\"delivery\",\"type\":\"text\"},{\"conditions\":\"true\",\"name\":\"type_of_note\",\"type\":\"text\"},{\"conditions\":\"true\",\"name\":\"date_start_invaite_sell\",\"type\":\"datetime\"},{\"conditions\":\"true\",\"name\":\"discount_rate\",\"type\":\"double\"},{\"conditions\":\"true\",\"name\":\"listing_agent\",\"type\":\"text\"},{\"conditions\":\"true\",\"name\":\"date_end_invaite_sell\",\"type\":\"datetime\"},{\"conditions\":\"true\",\"name\":\"del\",\"type\":\"number\"},{\"conditions\":\"true\",\"name\":\"deleted\",\"type\":\"number\"},{\"conditions\":\"true\",\"name\":\"guarantor\",\"type\":\"text\"},{\"conditions\":\"true\",\"name\":\"agregat_p_a\",\"type\":\"number\"},{\"conditions\":\"true\",\"name\":\"discount_min\",\"type\":\"double\"},{\"conditions\":\"true\",\"name\":\"issuuing_and_paying_agent\",\"type\":\"text\"},{\"conditions\":\"true\",\"name\":\"issuer\",\"type\":\"text\"},{\"conditions\":\"true\",\"name\":\"maturity_date\",\"type\":\"datetime\"},{\"conditions\":\"true\",\"name\":\"clearing_system\",\"type\":\"text\"},{\"conditions\":\"true\",\"name\":\"floating_rate_note\",\"type\":\"text\"},{\"conditions\":\"true\",\"name\":\"discount_max\",\"type\":\"double\"},{\"conditions\":\"true\",\"name\":\"fixed_rate_note\",\"type\":\"text\"},{\"conditions\":\"true\",\"name\":\"listing_and_admission_to_tr\",\"type\":\"text\"},{\"conditions\":\"true\",\"name\":\"isin\",\"type\":\"number\"},{\"conditions\":\"true\",\"name\":\"dealer\",\"type\":\"text\"},{\"conditions\":\"true\",\"name\":\"payment\",\"type\":\"money\"},{\"conditions\":\"true\",\"name\":\"ratings\",\"type\":\"text\"},{\"conditions\":\"true\",\"name\":\"issue_date\",\"type\":\"datetime\"}]",
                "Permissions": "{\"insert\": \"ContractConditions(\\\"MainCondition\\\")\", \"update\": \"ContractConditions(\\\"MainCondition\\\")\", \"new_column\": \"ContractConditions(\\\"MainCondition\\\")\"}"
            },
{
                "Type": "tables",
                "Name": "bidders_invaite",
                "Value": "",
                "Conditions": "ContractAccess(\"@1EditTable\")",
                "Menu": "",
                "Title": "",
                "Trans": "",
                "Columns": "[{\"conditions\":\"true\",\"name\":\"amount\",\"type\":\"number\"},{\"conditions\":\"true\",\"name\":\"status\",\"type\":\"number\"},{\"conditions\":\"true\",\"name\":\"member_id\",\"type\":\"number\"},{\"conditions\":\"true\",\"name\":\"offer_invaite_id\",\"type\":\"number\"}]",
                "Permissions": "{\"insert\": \"ContractConditions(\\\"MainCondition\\\")\", \"update\": \"ContractConditions(\\\"MainCondition\\\")\", \"new_column\": \"ContractConditions(\\\"MainCondition\\\")\"}"
            },
{
                "Type": "menu",
                "Name": "default_menu",
                "Value": "MenuItem(Title:Profile, Page:profile_view, Icon:\"fa icon-user\")\r\nMenuItem(Title:Membership, Page:members_list, Icon:\"fa icon-people\")\r\nMenuItem(Title:Notifications, Page:notifications_single, Icon:\"fa fa-bell-o\")\r\nMenuItem(Title:Roles, Page:roles_list, Icon:\"fa fa-list-ul\")\r\nMenuItem(Title:List of Invitations, Page:ListingOffer, Icon:\"fa fa-bell-o\")",
                "Conditions": "ContractAccess(\"@1EditMenu\")",
                "Menu": "",
                "Title": "default",
                "Trans": "",
                "Columns": "",
                "Permissions": ""
            },
{
                "Type": "menu",
                "Name": "admin_menu",
                "Value": "MenuItem(Title:\"Application\", Page:apps_list, Icon:\"icon-folder\")\r\nMenuItem(Title:\"Ecosystem parameters\", Page:params_list, Icon:\"icon-settings\")\r\nMenuItem(Title:\"Menu\", Page:menus_list, Icon:\"icon-list\")\r\nMenuItem(Title:\"Confirmations\", Page:confirmations, Icon:\"icon-check\")\r\nMenuItem(Title:\"Import\", Page:import_upload, Icon:\"icon-cloud-upload\")\r\nMenuItem(Title:\"Export\", Page:export_resources, Icon:\"icon-cloud-download\")\r\nMenuGroup(Title:\"Resources\", Icon:\"icon-share\"){\r\n\tMenuItem(Title:\"Pages\", Page:app_pages, Icon:\"icon-screen-desktop\")\r\n\tMenuItem(Title:\"Blocks\", Page:app_blocks, Icon:\"icon-grid\")\r\n\tMenuItem(Title:\"Tables\", Page:app_tables, Icon:\"icon-docs\")\r\n\tMenuItem(Title:\"Contracts\", Page:app_contracts, Icon:\"icon-briefcase\")\r\n\tMenuItem(Title:\"Application parameters\", Page:app_params, Icon:\"icon-wrench\")\r\n\tMenuItem(Title:\"Language resources\", Page:app_langres, Icon:\"icon-globe\")\r\n\tMenuItem(Title:\"Binary data\", Page:app_binary, Icon:\"icon-layers\")\r\n}\r\nMenuItem(Title:\"Dashboard\", Page:admin_dashboard, Icon:\"icon-wrench\")\r\nMenuItem(Title:\"List of Invitations\", Page:ListingOffer2, Icon:\"icon-wrench\")",
                "Conditions": "ContractConditions(\"MainCondition\")",
                "Menu": "",
                "Title": "",
                "Trans": "",
                "Columns": "",
                "Permissions": ""
            }
            ]
        }