[{"conditions":"false","name":"buyer_transferred_at","type":"number"},{"conditions":"ContractAccess(\"@1TaReject\")","name":"seller_reject_comment","type":"text"},{"conditions":"false","name":"amount","type":"money"},{"conditions":"false","name":"currency_type","type":"number"},{"conditions":"ContractAccess(\"@1TaReject\")","name":"manager_rejected_at","type":"number"},{"conditions":"ContractAccess(\"@1TaTransferSeller\")","name":"seller_transferred_at","type":"number"},{"conditions":"false","name":"amount_apl","type":"money"},{"conditions":"ContractAccess(\"@1TaReject\",\"@1TaTransferSeller\")","name":"key_id_seller","type":"number"},{"conditions":"ContractAccess(\"@1TaReject\")","name":"seller_rejected_at","type":"number"},{"conditions":"false","name":"key_id_sale_apl_admin","type":"number"},{"conditions":"ContractAccess(\"@1TaReject\")","name":"manager_reject_comment","type":"text"},{"conditions":"ContractAccess(\"@1TaReject\",\"@1TaTransferManager\")","name":"key_id_sale_apl_manager","type":"number"},{"conditions":"false","name":"created_at","type":"number"},{"conditions":"false","name":"key_id_buyer","type":"number"}
]