[
    {
        "conditions": "true",
        "name": "deleted_at",
        "type": "number"
    },
    {
        "conditions": "true",
        "name": "finaled_at",
        "type": "number"
    },
    {
        "conditions": "true",
        "name": "uploaded_at",
        "type": "number"
    },
    {
        "conditions": "true",
        "name": "imported_at",
        "type": "number"
    },
    {
        "conditions": "true",
        "name": "kid",
        "type": "number"
    },
    {
        "conditions": "true",
        "name": "rid",
        "type": "number"
    },
    {
        "conditions": "true",
        "name": "file_name",
        "type": "varchar"
    },
    {
        "conditions": "true",
        "name": "drilling_id",
        "type": "number"
    },
    {
        "conditions": "true",
        "name": "coil_id",
        "type": "number"
    },
    {
        "conditions": "true",
        "name": "binary_id",
        "type": "number"
    }
]